{
	"connection_key": "response",
	"result": true,
	"redis_key": "abcdefg",
	"filepath": "/var/lib/aion/Data/rededge_sdc/abcdef.json",
	"SurveyRootCollection": {
        "ObjectID": "",
        "ID": "4",
        "Version": "",
        "Name": "",
        "NameLanguageCode": "",
        "NameLanguageCodeText": "",
        "TypeCode": "",
        "TypeCodeText": "",
        "CategoryCode": "",
        "CategoryCodeText": "",
        "ValidFromDate": "",
        "ValidToDate": null,
        "LifeCycleStatusCode": "",
        "LifeCycleStatusCodeText": "",
        "PreviousAnswersIndicator": true,
        "PreviousRuntimeProductsIndicator": false,
        "MatrixViewIndicator": false,
        "PaginationIndicator": false,
        "IncludeProductListIndicator": false,
        "SalesOrganisationID": "",
        "ServiceOrganisationID": "",
        "EntityLastChangedOn": "",
        "ETag": "",
        "TotalMaximumScoreValue": 0,
        "TotalMinimumScoreValue": 0,
        "SurveyCreationDateTime": ""
	},
	"api_schema": "SurveyDesign",
	"accepter": ["SurveyRootCollection"],
	"survey_design_code": "4",
	"deleted": false
}
